peelpreter/__init__.py
peelpreter/__main__.py
peelpreter/astt/__init__.py
peelpreter/astt/astt.py
peelpreter/error/__init__.py
peelpreter/error/error.py
peelpreter/evaluator/__init__.py
peelpreter/evaluator/evaluator.py
peelpreter/evaluator/mbuiltins.py
peelpreter/lexer/__init__.py
peelpreter/lexer/tokenizer.py
peelpreter/objectt/__init__.py
peelpreter/objectt/enviroment.py
peelpreter/objectt/objectt.py
peelpreter/parser/__init__.py
peelpreter/parser/parser.py
peelpreter/token_type/__init__.py
peelpreter/token_type/token_type.py
Peelpreter-1.7.4.dist-info/COPYING
Peelpreter-1.7.4.dist-info/METADATA
Peelpreter-1.7.4.dist-info/WHEEL
Peelpreter-1.7.4.dist-info/entry_points.txt
Peelpreter-1.7.4.dist-info/top_level.txt
Peelpreter-1.7.4.dist-info/RECORD
