Metadata-Version: 2.1
Name: Peelpreter
Version: 1.7.4
Summary: A interpreter written in Python for the language, Monkey
Author: Jeebak Samajdwar
Maintainer: Jeebak Samajdwar
License: GPL
Project-URL: Repository, https://github.com/GogiBoy102/Peelpreter
Keywords: monkey,interpreter,ast,treewalker,vm,programing language,language
Classifier: License :: OSI Approved :: GNU General Public License (GPL)
Classifier: License :: OSI Approved :: GNU General Public License v3 or later (GPLv3+)
Classifier: Environment :: Console
Classifier: Intended Audience :: Developers
Classifier: Operating System :: OS Independent
Classifier: Programming Language :: Python
Classifier: Programming Language :: Python :: 3
Classifier: Programming Language :: Python :: 3 :: Only
Classifier: Programming Language :: Python :: 3.7
Classifier: Programming Language :: Python :: 3.8
Classifier: Programming Language :: Python :: 3.9
Classifier: Programming Language :: Python :: 3.10
Classifier: Programming Language :: Python :: 3.11
Classifier: Programming Language :: Python :: 3.12
Classifier: Topic :: Software Development
Classifier: Topic :: Software Development :: Interpreters
Classifier: Typing :: Typed
Requires-Python: >=3.7
License-File: COPYING
Requires-Dist: pyreadline3
